{
    "equipments": [
        {
            "categoryCode": "head-top",
            "items": [
                {
                    "id": "82f88a48-f3a1-40da-8750-81e4b1a06eaf",
                    "name": "席琳的蝴蝶結",
                    "star": 5,
                    "comments": [
                        "預算夠的話這個還是最強，畢竟打王傷害會很高，不過因為我自己覺得釋放很麻煩，而且傷害也不如風念，所以我吃王時會轉風念。"
                    ]
                },
                {
                    "id": "7668f0b3-6db2-4783-a15c-dc41d9c861ca",
                    "name": "超時空頭冠(咒術士)",
                    "star": 2,
                    "comments": [
                        "不怎麼適合火咒。"
                    ]
                },
                {
                    "id": "7321c8d4-e3ae-4943-bfc1-7769c4e5d26c",
                    "name": "神秘魔力石帽子",
                    "star": 4.5,
                    "comments": [
                        "最大優點是有減少碧血隕石的CD時間，如果+14的話減少2.4秒，非常多，額外的好處就是魔精附魔減固詠，不過其實不太缺就是了，頂多是鞋子可以選擇智慧靴。"
                    ]
                },
                {
                    "id": "58f0eda6-cb18-4ce3-830e-736144eb8b5b",
                    "name": "魔幻羽毛髮夾",
                    "star": 1.5,
                    "comments": [
                        "我覺得過氣了"
                    ]
                },
                {
                    "id": "f13f0ec2-dfec-401c-be73-5b8761a8f37e",
                    "name": "長長貓耳朵帽子",
                    "star": 1.5,
                    "comments": [
                        "雖然有破防，可以搭配職業2.0套和贖罪達到破防100%，但本身效果太爛，我覺得不太OK。"
                    ]
                },
                {
                    "id": "2aaebfbc-ea09-4848-a7fc-32361a93c724",
                    "name": "修咖巴殷的黑貓耳朵",
                    "star": 0.5,
                    "comments": [
                        "完全不適合火咒，畢竟放完技能後怪死了技能進CD，用不到他的觸發效果。"
                    ]
                }
            ],
            "cards": [
                {
                    "id": "64f86127-13f3-4121-b74c-104f400a8bfc",
                    "name": "齊爾-D-01卡片",
                    "star": 1,
                    "comments": [
                        "因為碧血隕石目前沒有辦法秒7，所以齊爾卡也就無用武之地，而且碧血隕石共延只有0.5秒，其實也沒有很需要這張卡。"
                    ]
                },
                {
                    "id": "aee3bc22-633e-4950-b353-01cffb868bc9",
                    "name": "封印齊爾-D-01卡片",
                    "star": 0.5,
                    "comments": [
                        "同正卡。"
                    ]
                },
                {
                    "id": "73c82d11-42e8-4f0e-bff2-bd1d37a71093",
                    "name": "貝思波卡片",
                    "star": 5,
                    "comments": [
                        "搭配影子2.0和贖罪可以達到BOSS破防100%"
                    ]
                },
                {
                    "id": "8fcb7a2d-4fd3-4035-808c-b47464f3aab3",
                    "name": "封印貝思波卡片",
                    "star": 5,
                    "comments": [
                        "同正卡"
                    ]
                },
                {
                    "id": "1aeea3b1-3373-47dc-8799-8912b58d8b31",
                    "name": "潘利爾卡片",
                    "star": 4.5,
                    "comments": [
                        "加很多MATK，想撐傷害可以考慮，但我覺得CP值略低。"
                    ]
                },
                {
                    "id": "45f68dde-b6f4-43e5-90f3-f474f024b6ae",
                    "name": "闇●超魔導師 凱特莉娜卡片",
                    "star": 5,
                    "comments": [
                        "無視所有小怪的魔防，練功清怪好用。"
                    ]
                },
                {
                    "id": "ec73d56b-1156-456f-b33c-d33820127fca",
                    "name": "封印闇●超魔導師 凱特莉娜卡片",
                    "star": 1,
                    "comments": [
                        "效果同正卡，額外的副作用可無視，練功清怪好用。"
                    ]
                },
                {
                    "id": "00555cbd-7302-4cab-9376-98eabcf903bf",
                    "name": "元素鬼火(紅)卡片",
                    "star": 4,
                    "comments": [
                        "因為不缺延遲，所以頭上選擇寬鬆很多，插這種屬性傷害卡也是不無小補。"
                    ]
                },
                {
                    "id": "8526c86b-e49c-4250-b27e-ba8e133b6e2b",
                    "name": "變種腔棘魚卡片",
                    "star": 0.5,
                    "comments": [
                        "毫無王卡的威嚴，MATK%加的又少，還要扣血，感覺插上去是一種懲罰。"
                    ]
                },
                {
                    "id": "fec8ace5-179a-4c90-885d-40b791712ed7",
                    "name": "弱化的潘利爾卡片",
                    "star": 0.5,
                    "comments": [
                        "乞丐卡，不如不插存錢買更好的。"
                    ]
                }
            ]
        },
        {
            "categoryCode": "head-middle",
            "items": [
                {
                    "id": "d2e2c301-d7f3-4f22-af7d-777bc72e98bc",
                    "name": "太陽眼鏡",
                    "star": 5,
                    "comments": [
                        "主要是能搭配暴徒用。"
                    ]
                },
                {
                    "id": "9ef44931-4623-4029-b9aa-ca64f69c9f1f",
                    "name": "眼鏡",
                    "star": 5,
                    "comments": [
                        "同太陽眼鏡"
                    ]
                },
                {
                    "id": "0607293b-06f9-4b39-9f52-8de29ca25b94",
                    "name": "新浪潮墨鏡",
                    "star": 0.5,
                    "comments": [
                        "我認為現階段火咒不太缺延遲。"
                    ]
                },
                {
                    "id": "7dbece25-252f-4b97-8486-503d77c2fd11",
                    "name": "新浪潮墨鏡0s",
                    "star": 0.5,
                    "comments": [
                        "同有洞的。"
                    ]
                },
                {
                    "id": "90d38a4f-0ab2-474b-b43d-a8d85fb03568",
                    "name": "柯杜威之耳",
                    "star": 5,
                    "comments": [
                        "MATK加很多，沒洞也對火咒影響不大，畢竟不需要齊爾。"
                    ]
                },
                {
                    "id": "ab0adea1-ddce-4fc2-ac65-5959e0c88346",
                    "name": "惡魔小跟班",
                    "star": 3.5,
                    "comments": [
                        "就是要他的一洞，可以插增傷或是破防卡。"
                    ]
                },
                {
                    "id": "5cdd405f-3890-4c1c-89a7-9aa4e48f15b9",
                    "name": "妖精長耳朵飾",
                    "star": 3.5,
                    "comments": [
                        "就是要他的一洞，可以插增傷或是破防卡。"
                    ]
                },
                {
                    "id": "b161e12e-a887-420f-a2cd-a71b8c3bfa9b",
                    "name": "影子推助器",
                    "star": 3.5,
                    "comments": [
                        "就是要他的一洞來插卡，本身的效果火咒用不太到。"
                    ]
                },
                {
                    "id": "3049a8ee-a1e7-41ea-b0f6-220d65c92871",
                    "name": "魔力之星",
                    "star": 4,
                    "comments": [
                        "必點的INT就有+火屬性傷害，搭配魔力星環套裝拚裝備無詠和屬性、BOSS增傷、減固詠還不錯用，但價錢被炒得有點高。"
                    ]
                },
                {
                    "id": "4c4f2b6c-2706-4072-9350-8ae412d29c27",
                    "name": "太陽眼鏡",
                    "star": 3.5,
                    "comments": [
                        "沒洞的太陽眼鏡，主要就是搭配暴徒用"
                    ]
                },
                {
                    "id": "d0cc8a21-94dc-4350-9f02-8e44c510fc00",
                    "name": "眼鏡",
                    "star": 3.5,
                    "comments": [
                        "同沒洞的太陽眼鏡"
                    ]
                }
            ],
            "cards": []
        },
        {
            "categoryCode": "head-bottom",
            "items": [
                {
                    "id": "a1549ed6-8f9d-4bcf-b4af-5e46f00d840d",
                    "name": "暴徒領巾",
                    "star": 5,
                    "comments": [
                        "首選頭下，搭配太陽眼鏡或眼鏡可以加大量的 魔攻、攻速、血量，雖然台版被閹割，但還是非常強。"
                    ]
                },
                {
                    "id": "8f42b002-240f-4ef8-85b2-61a4b1dd0a64",
                    "name": "夢魘古城旁觀者",
                    "star": 0.5,
                    "comments": [
                        "不缺延遲。"
                    ]
                },
                {
                    "id": "a9167d86-9158-46e1-a99c-bf1aa3a6e518",
                    "name": "小巴風特降落傘",
                    "star": 0.5,
                    "comments": [
                        "不缺延遲和攻速。"
                    ]
                },
                {
                    "id": "5fda17f3-b8d0-44f1-a74d-f95e842b69b4",
                    "name": "貓熊氣球",
                    "star": 0.5,
                    "comments": [
                        "同樣不缺。"
                    ]
                },
                {
                    "id": "b66571b3-c44b-463a-ace5-454a03d8696c",
                    "name": "神木嫩葉",
                    "star": 5,
                    "comments": [
                        "還不錯，可以撐傷害。"
                    ]
                },
                {
                    "id": "5be4be88-7f3b-4483-bb25-04a38d4afb73",
                    "name": "嘴叼狐尾草",
                    "star": 0.5,
                    "comments": [
                        "基本上固詠會溢出。"
                    ]
                },
                {
                    "id": "9e6e5389-94a8-43ae-b8c5-5e7e36849479",
                    "name": "扭曲的超時空",
                    "star": 0.5,
                    "comments": [
                        "超級沒用。"
                    ]
                },
                {
                    "id": "fe567e9c-f3ad-4eac-b2fb-9feba92e6b79",
                    "name": "邪惡氣息",
                    "star": 2,
                    "comments": [
                        "EDDA研究所出產的新頭下，搭配戰死斗會有很強力的效果，但主要看點是提供大量延遲、減變詠和攻速，火咒用不太到。"
                    ]
                },
                {
                    "id": "ed53e0d0-2c69-4692-bf69-657aa5c50c1b",
                    "name": "雙管加農砲",
                    "star": 0.5,
                    "comments": [
                        "不缺。"
                    ]
                },
                {
                    "id": "58721428-3d88-43cb-9c23-4f955c7bdfd5",
                    "name": "永恆波利氣球",
                    "star": 3,
                    "comments": [
                        "搭配永恆之翼可以有不錯的效果，算是平民好用裝備。"
                    ]
                },
                {
                    "id": "ad03d2a0-8429-450f-bc5c-e5e61e359359",
                    "name": "魔力星陣",
                    "star": 4,
                    "comments": [
                        "搭配魔力之星套用的，這套是小資裝的定位，但魔力之星卻被炒到很誇張的價錢，我個人認為已經完全沒有買的必要了，要花這麼多不如去買暴徒。不過單穿也可以拿來減固詠就是了。"
                    ]
                },
                {
                    "id": "02ed5549-ffb2-49d1-aa25-5246736b4b4e",
                    "name": "時光超越天地樹苗",
                    "star": 5,
                    "comments": [
                        "整套好附魔搭配滅世靴傷害會是版本最高，但跟席琳整套沒差多少，這個比席琳還綁裝，又要拚附魔，而且市面上多是物理系列的，建議錢很多再去搞。"
                    ]
                }
            ],
            "cards": []
        },
        {
            "categoryCode": "body",
            "items": [
                {
                    "id": "7ff4b389-c319-4f5a-a600-30d7292e51c7",
                    "name": "朱比特輕甲",
                    "star": 3.5,
                    "comments": [
                        "現階段這件裝只能說是堪用了，不過火咒沒必要使用，而且如果搭配滅世靴的話，這件效果又會再打折。"
                    ]
                },
                {
                    "id": "aef1b05d-833d-4f17-aae8-655c7180b012",
                    "name": "幻象機甲B型",
                    "star": 4,
                    "comments": [
                        "非常好入手的一件衣服，價格低、效果強，不過我比個人比較喜歡智慧長袍，比較好撐素質無詠。"
                    ]
                },
                {
                    "id": "b793920f-049e-43e7-b3f2-5cc77e0ba6a1",
                    "name": "奉承外袍",
                    "star": 2,
                    "comments": [
                        "已經過氣了，除非你上面插了滅絕古埃及王之類的，才有可能繼續用。"
                    ]
                },
                {
                    "id": "c0cab7ab-de12-4d5f-ba0c-b83c8aae60ea",
                    "name": "施密特國王新衣",
                    "star": 1.5,
                    "comments": [
                        "近期才出的EDDA國王的裝備，但能力實在不怎麼樣。"
                    ]
                },
                {
                    "id": "3e93875c-8c5e-471e-a369-4c0359116f4f",
                    "name": "智慧湧現魔甲",
                    "star": 0.5,
                    "comments": [
                        "沒什麼用，附魔的延遲也不缺。"
                    ]
                },
                {
                    "id": "f8ce81ba-96fe-414a-a0bf-7e3fefb4bbe0",
                    "name": "大法師爭戰鎧甲",
                    "star": 0.5,
                    "comments": [
                        "適合地牛咒，火咒用不到。"
                    ]
                },
                {
                    "id": "522b4473-7617-4eb9-82f3-064193d17008",
                    "name": "月全蝕魔力外袍",
                    "star": 4,
                    "comments": [
                        "對於撐硬來說蠻不錯的，提高生存力的選擇。"
                    ]
                },
                {
                    "id": "aa30205d-934f-467c-9697-9c88c1d033cb",
                    "name": "時光超越湧現鎧甲",
                    "star": 5,
                    "comments": [
                        "泛用度很高的裝備，原本已經過氣，經過了加強附魔和頭下時光超越苗的加強，直接變成現階段最強裝備，但附魔終究是看臉，而且綁好幾件裝，鞋子的效果也吃不到，畢竟滅世靴還是目前最破格的存在，硬要換掉反而傷害會降。我自己覺得未來應該會有更是合法系的特別裝出現。"
                    ]
                },
                {
                    "id": "354fc73f-c7af-4e50-b842-4549fd0be824",
                    "name": "智慧長袍",
                    "star": 4,
                    "comments": [
                        "對天使/惡魔特化的裝備，而且INT給非常多，換上滅世靴後如果不另外找裝備補素質，就算200等也不太能夠不靠20料就達到無詠，這件裝備解決了這個問題，"
                    ]
                },
                {
                    "id": "ce36e1ef-5aa5-42de-92bf-2b6940e56fe0",
                    "name": "靈巧長袍",
                    "star": 0.5,
                    "comments": [
                        "同樣是對天使惡魔特化裝備，特點是如果附到DEX胸針會有-0.3秒固詠的效果，比較適合彗星咒。"
                    ]
                },
                {
                    "id": "4743d2fa-30fd-40e6-8b81-735c5441d938",
                    "name": "藍龍鎧甲",
                    "star": 0.5,
                    "comments": [
                        "主要賣點我覺得是減固詠，感覺蠻適合彗星咒，但風念的話我覺得不太適合。"
                    ]
                },
                {
                    "id": "83a34f0a-ceaa-4e81-b882-a91053acd6c9",
                    "name": "席琳的沾血黑禮服",
                    "star": 0.5,
                    "comments": [
                        "日服引進的閹割裝備，被砍太大，完全不實用。"
                    ]
                },
                {
                    "id": "f44e718e-93c6-4dcb-8d6c-20ab44fb3ee3",
                    "name": "基米的沾血黑禮服",
                    "star": 5,
                    "comments": [
                        "首選裝備，搭配席琳整套傷害很高，但並不是打什麼都最頂尖傷害，天使惡魔傷害可能會輸智袍、技能傷害可能輸技能附魔自動甲，但很萬用。"
                    ]
                },
                {
                    "id": "5773016e-55cc-4aa2-86fd-46a58cbb2522",
                    "name": "瓦爾哈拉之心●布林喜德",
                    "star": 5,
                    "comments": [
                        "SE城戰的新神器，效果蠻強的，很萬用，不過現在應該是非常稀有，價格應該是很恐怖。不過無詠的方式就跟禮服一樣。"
                    ]
                },
                {
                    "id": "e4805fa1-0f7d-4794-b69e-e91ffcf24066",
                    "name": "全自動機甲B型",
                    "star": 4.5,
                    "comments": [
                        "17.2新出的系列裝備，跟17.1的幻象系列很像，但最大的不同也是最大的賣點就是多了史詩模組，對特定技能增加傷害的附魔，不過火咒的技能增傷通常都非常高，建議如果要用這件可以選擇MATK或是魅影念咒附魔。"
                    ]
                }
            ],
            "cards": [
                {
                    "id": "6d7fb2e0-c534-4d9c-81f2-b938ebd3155e",
                    "name": "滅絕古埃及王卡片",
                    "star": 5,
                    "comments": [
                        "拚傷害首選卡片，提供大量增傷，對不死屬、暗屬、不死型、惡魔型增加50%傷害，有機會同時觸發兩個+50%傷害，RO這些屬性的怪非常多，還有G社最愛的各式各樣的古城副本，例如現在正夯的挑戰古城，都是這張卡發揮的場所，你看到有人打出超級誇張的傷害一定是靠這張卡打的。"
                    ]
                },
                {
                    "id": "c25ab4c9-5561-40f0-b258-499f0f92e2e4",
                    "name": "塔奧群卡卡片",
                    "star": 4,
                    "comments": [
                        "保命首選卡片，活著才是輸出，而且滅絕古埃也不是每次都能發揮效果，這張跟傷害卡就看大家自己取捨。"
                    ]
                },
                {
                    "id": "0bd31ba7-8c83-4670-a7a7-39f971c56a24",
                    "name": "封印塔奧群卡卡片",
                    "star": 3.5,
                    "comments": [
                        "省錢的保命選擇，好處是可以隨時拔卡。"
                    ]
                },
                {
                    "id": "f7f6aa21-fe8a-42b1-9c33-0abe9baaf70d",
                    "name": "無限塔奧群卡卡片",
                    "star": 0.5,
                    "comments": [
                        "我個人是覺得只+10000還要扣10AGI蠻爛的，應該不是設計給三轉職業用的，所以不推薦。"
                    ]
                },
                {
                    "id": "9c2fc595-c1b7-42b7-bceb-0e5f564c0189",
                    "name": "覺醒闇答萊屍卡片",
                    "star": 4,
                    "comments": [
                        "泛用增傷卡片，但副作用強但加的東西很普通，我沒有很喜歡，但如果沒辦法觸發滅絕古埃及王的情況，這張幾乎是唯一選擇了。"
                    ]
                },
                {
                    "id": "1a205887-d9e5-42df-8a5f-ca0a4068d627",
                    "name": "闇答萊屍卡片",
                    "star": 3.5,
                    "comments": [
                        "效果比較差，但便宜"
                    ]
                },
                {
                    "id": "101a0817-92c1-4022-84f9-d2ccfc8a0846",
                    "name": "骷髏觸角魔卡片",
                    "star": 4,
                    "comments": [
                        "簡單暴力的+100MATK，很泛用的增傷，再滅絕古埃及王無法觸發時的另一選擇。"
                    ]
                },
                {
                    "id": "524010fe-f445-4b8f-a6ac-4bcac0d6110b",
                    "name": "闇●智者 西里亞卡片",
                    "star": 3.5,
                    "comments": [
                        "沒有副作用的泛用增傷卡片，但有自詠的疑慮。"
                    ]
                },
                {
                    "id": "9d0df438-ee94-4cb6-8b5a-3d3bbc50f9fb",
                    "name": "封印闇●智者 西里亞卡片",
                    "star": 2.5,
                    "comments": [
                        "加的有點太少了，不太建議。"
                    ]
                },
                {
                    "id": "9a56822a-baf0-4b33-a8a1-da4f846363c1",
                    "name": "幻影夢魘卡片",
                    "star": 2,
                    "comments": [
                        "目前多數平民法師的選擇，有MATK又有無副作用防斷。"
                    ]
                },
                {
                    "id": "f140e28e-b087-4f50-9d9d-b3fd34b49750",
                    "name": "卡崙卡片",
                    "star": 4,
                    "comments": [
                        "搭配月全蝕魔力外袍用的，其他裝備不要插這張。"
                    ]
                },
                {
                    "id": "88b7b010-6c26-454b-9910-22713f1df167",
                    "name": "尼德霍格幻影卡片",
                    "star": 3,
                    "comments": [
                        "搭配守護精靈祈禱之鞋有BOSS增傷40%，對於滅絕古埃及王無法生效的場合來說蠻實用的。不過缺點也很明顯就是綁裝，加上火咒頂裝會是滅世靴，如果使用這套就會卡到滅世。"
                    ]
                },
                {
                    "id": "9a065da2-19f2-4fc2-a300-7136f2496126",
                    "name": "闇●神官 瑪嘉雷特卡片",
                    "star": 3,
                    "comments": [
                        "搭配阿斯戒的時候才用得到，其他時候都不考慮。"
                    ]
                },
                {
                    "id": "27c41a25-bdba-466e-b2d8-25da68baa85b",
                    "name": "封印滅絕古埃及王卡片",
                    "star": 4.5,
                    "comments": [
                        "同正卡，但加的傷害少一半，不過現在價錢有點太誇張了。"
                    ]
                },
                {
                    "id": "50efc823-c00b-43b2-99a9-159cd8a1575a",
                    "name": "夢魘紅椒卡片",
                    "star": 5,
                    "comments": [
                        "跟滅絕古埃及王同樣類型的卡片，不過其中只有對無形和聖屬得會比較常用到，魚貝和水屬可能就很少了"
                    ]
                },
                {
                    "id": "9671f457-8a45-4cf9-9e6f-61e497b82a29",
                    "name": "紅椒卡片",
                    "star": 4.5,
                    "comments": [
                        "弱化版的夢魘紅椒卡。"
                    ]
                }
            ]
        },
        {
            "categoryCode": "weapon",
            "items": [
                {
                    "id": "a34dc2aa-fdc3-4fb8-8b3f-9b5e6d293d95",
                    "name": "碧血玫瑰魔杖",
                    "star": 5,
                    "comments": [
                        "火咒第一選擇，加一堆火傷和碧血隕石傷害。"
                    ]
                },
                {
                    "id": "e2aae17d-0a3d-4e16-aa3c-2d174eb2ac91",
                    "name": "紅魔鬼法杖-OS",
                    "star": 4,
                    "comments": [
                        "優點是有體型傷害，和機率觸發的火傷。"
                    ]
                },
                {
                    "id": "93c7a302-2174-4b61-8c63-2b944041f56d",
                    "name": "向日葵少年魔杖",
                    "star": 0.5,
                    "comments": [
                        "雙手杖沒有前途，不能拿盾傷害又沒多高，而且這把也過氣了。"
                    ]
                },
                {
                    "id": "e0e29031-7234-4902-a8eb-2c132ca5e369",
                    "name": "藍焰彩杖",
                    "star": 0.5,
                    "comments": [
                        "雙手杖沒有前途，不能拿盾傷害又沒多高。"
                    ]
                },
                {
                    "id": "4cbec776-9b8e-460f-ac9f-7ef312d17a05",
                    "name": "幻影生存的魔杖",
                    "star": 0.5,
                    "comments": [
                        "身為雙手杖給的MATK有點低，只有240，靠精煉和套裝的特效彌補，但現在雙手杖真的很爛，雖然這把套裝也有體型增傷，但只有中小型，小型基本上沒什麼用，大型才是重點。"
                    ]
                },
                {
                    "id": "1f177407-7290-4d29-bb79-af7431a0b568",
                    "name": "邪惡權杖",
                    "star": 0.5,
                    "comments": [
                        "沒啥用了，而且只有一洞就輸在起跑點。"
                    ]
                },
                {
                    "id": "315212f7-0b3b-4b7c-a94f-facc3a4c0d06",
                    "name": "邪惡魔杖",
                    "star": 0.5,
                    "comments": [
                        "同邪惡權杖，但是是雙手杖，只要是雙手杖就不用我再多說了。"
                    ]
                },
                {
                    "id": "3064489c-2ef7-4bfe-b514-181ff6aa6769",
                    "name": "鋼鐵魔杖",
                    "star": 2,
                    "comments": [
                        "這把對火咒唯一好處就是低等就能拿。"
                    ]
                },
                {
                    "id": "5ff8ab7f-281a-42be-8314-b45cbc681176",
                    "name": "皇室魔杖",
                    "star": 0.5,
                    "comments": [
                        "挑戰古城出產的武器，是雙手杖，對火咒完全沒幫助。"
                    ]
                },
                {
                    "id": "54ca0474-5258-431e-845a-65b195b6f434",
                    "name": "皇室高級魔杖",
                    "star": 3.5,
                    "comments": [
                        "加了一點火傷和技能傷害，如果有搭配套裝的話會在高一些，火咒屬於門檻低的配置，所以施密特套也可以考慮。"
                    ]
                },
                {
                    "id": "7f622f75-c7be-46f2-9be4-df33692fe516",
                    "name": "守護精靈魔杖",
                    "star": 0.5,
                    "comments": [
                        "3級武器，對於綁定真咒卡的火咒來說非常不利。"
                    ]
                },
                {
                    "id": "74537f26-3a46-4189-8453-8fb8c152093d",
                    "name": "幻影大巫師之杖",
                    "star": 1,
                    "comments": [
                        "主要是搭配幻影生存斗篷時可以增加地獄火傷害，可是咒術\"優化\"後這招變成有CD，實用性打個大問號，而且這招本來就不是主力，只是打聖4時的不得以手段。"
                    ]
                },
                {
                    "id": "1a7be349-36c4-46eb-a7ae-9faadf3beb3a",
                    "name": "黑暗的荊棘骷髏杖",
                    "star": 0.5,
                    "comments": [
                        "火咒不缺延遲。"
                    ]
                },
                {
                    "id": "b2676ff1-759b-4d92-92a3-4f7778525998",
                    "name": "破壞之杖",
                    "star": 0.5,
                    "comments": [
                        "曾經的平民法杖，現在已經不推薦使用。"
                    ]
                },
                {
                    "id": "398ee202-c632-4d2c-aaf6-056ab940a22b",
                    "name": "赤火焰魔杖",
                    "star": 0.5,
                    "comments": [
                        "完全沒用別買。"
                    ]
                },
                {
                    "id": "05e59a92-ae09-4001-aef8-93f74faa22b6",
                    "name": "焊接魔杖",
                    "star": 4.5,
                    "comments": [
                        "礦山3F開放後的首選武器，超高減延遲又有可以有三條附魔加MATK和BOSS傷害，就算沒附魔也很強，本身還有加火傷，觸發體型傷害增加的機率也頗高。"
                    ]
                },
                {
                    "id": "564ee988-2d78-4ac4-84d5-9010c9adc366",
                    "name": "感測魔杖",
                    "star": 3,
                    "comments": [
                        "雙手杖版本的焊接魔杖，沒有強到需要犧牲盾牌。"
                    ]
                }
            ],
            "cards": [
                {
                    "id": "acf6df17-3ce9-40e0-8054-379edf96aae1",
                    "name": "真●咒術士卡片",
                    "star": 5,
                    "comments": [
                        "幾乎是火咒唯一選擇了。"
                    ]
                },
                {
                    "id": "ddc041a1-6a0d-4ed0-b257-79b6a0e2a58a",
                    "name": "變異白色騎士卡片",
                    "star": 4,
                    "comments": [
                        "如果技能增傷過高的情況可以混插這張，但我自己還是喜歡無腦插真咒最泛用，畢竟這個Build的優勢就是練功打雜怪。"
                    ]
                },
                {
                    "id": "0c832ae1-8916-494d-a566-f5225ebee6c5",
                    "name": "多彩泰迪熊卡片",
                    "star": 1,
                    "comments": [
                        "不推薦。"
                    ]
                },
                {
                    "id": "67bedc3b-edea-4370-b265-2d0b1a76c2e1",
                    "name": "靈魂碎片卡片",
                    "star": 1,
                    "comments": [
                        "不推薦。"
                    ]
                },
                {
                    "id": "79efd5a0-52c2-4c87-8223-4bff53a56225",
                    "name": "時間支配者卡片",
                    "star": 1,
                    "comments": [
                        "雖然現在的配裝MATK%已經不會像以前一樣這麼多，但還是超爛。這張卡只能等G社拯救了。"
                    ]
                },
                {
                    "id": "f6943e54-3ea0-4fcf-b725-98f1a87b62e9",
                    "name": "封印時間支配者卡片",
                    "star": 0.5,
                    "comments": [
                        "正卡都輸小怪卡了，封印更不用說。"
                    ]
                },
                {
                    "id": "f83fd836-365c-406d-b7af-ccdd53462e0c",
                    "name": "席琳基米卡片",
                    "star": 0.5,
                    "comments": [
                        "20%的都沒搞頭了，基本上這些10%MATK的卡片都是沒有用了。"
                    ]
                },
                {
                    "id": "aeb34e53-ccd6-451b-9f25-ff7b0ff6abb0",
                    "name": "不朽風魔巫師卡片",
                    "star": 0.5,
                    "comments": [
                        "20%的都沒搞頭了，基本上這些10%MATK的卡片都是沒有用了。"
                    ]
                },
                {
                    "id": "e5575dea-e4b8-47eb-a8af-adc6b228199a",
                    "name": "天使方體惡魔卡片",
                    "star": 0.5,
                    "comments": [
                        "這個build打挑戰王很無力，不必特別去撐惡魔傷害。"
                    ]
                },
                {
                    "id": "bfe82ba8-b11b-45af-8d9d-dddf2acfbfb6",
                    "name": "紅肉食人火龍果卡片",
                    "star": 2,
                    "comments": [
                        "我認為還是不會有真咒好用，而且還要+14才有30%。"
                    ]
                }
            ]
        },
        {
            "categoryCode": "shield",
            "items": [
                {
                    "id": "b361d04c-b233-469c-9ffc-3d5f71d2c43b",
                    "name": "神聖騎士盾牌",
                    "star": 5,
                    "comments": [
                        "目前RO最強的盾牌，能夠付魔BOSS無視魔防30~60%，搭配影子職業2.0輕鬆無視100%魔防不用切裝，屬於夢幻逸品。不過現在天衣無縫風暴套出來後這件裝已經變成時代的眼淚了。"
                    ]
                },
                {
                    "id": "0fa63dbb-40bc-41ef-932f-4d3d73421cbc",
                    "name": "血腥騎士盾牌",
                    "star": 3,
                    "comments": [
                        "神聖盾的副產品，屬性都略低於神聖盾，但沒有第三條附魔，沒有無視BOSS魔防配裝上就差很多了，不過基本上現在多數中高階盾牌都是用這面。"
                    ]
                },
                {
                    "id": "e0fa7890-4274-4d3a-93a6-6dfea0bf44cc",
                    "name": "瘋狂兔寶寶",
                    "star": 1,
                    "comments": [
                        "加的東西都用不太到。"
                    ]
                },
                {
                    "id": "4b387ba9-c2d2-4e02-b66c-2413911d614a",
                    "name": "被詛咒的瘋狂兔寶寶",
                    "star": 1,
                    "comments": [
                        "加很多攻速的盾牌，致命缺點是沒有洞。"
                    ]
                },
                {
                    "id": "176a066e-e92a-44d1-83f7-d9b0d013f1ca",
                    "name": "守護精靈神盾",
                    "star": 0.5,
                    "comments": [
                        "用不到。"
                    ]
                },
                {
                    "id": "aa551a8d-fe3c-4e37-a4bc-a613478c6331",
                    "name": "墮落天使神盾",
                    "star": 0.5,
                    "comments": [
                        "用不到。"
                    ]
                },
                {
                    "id": "c6dbef2a-7011-4919-8c34-1e239da6aa7e",
                    "name": "聖之羽翼神盾",
                    "star": 3,
                    "comments": [
                        "本來沒啥用，但後來開放附魔後算是可以用，因為有加傷害。"
                    ]
                }
            ],
            "cards": [
                {
                    "id": "11707d60-348a-4679-9d93-63c72d5d446b",
                    "name": "黃金蟲卡片",
                    "star": 5,
                    "comments": [
                        "打王的時候很好用，像挑戰古城、波士尼亞這種高強度的地圖，會很明顯感受到黃金蟲的威力，有和沒有是兩種世界。"
                    ]
                },
                {
                    "id": "e60918f6-76c2-4f15-90e0-42abed241df2",
                    "name": "變異卡利斯格卡片",
                    "star": 4,
                    "comments": [
                        "本傷減傷就蠻優秀，再搭配變異白色騎士卡片可以進一步增加體型魔法傷害。"
                    ]
                },
                {
                    "id": "19a89ba1-2b41-46df-8c85-389cd4b0a350",
                    "name": "卡利斯格騎士團卡片",
                    "star": 2.5,
                    "comments": [
                        "物理版的變異卡利斯格卡，以前蠻泛用的一張減傷卡，現在有更好的選擇了。"
                    ]
                },
                {
                    "id": "efa4adb8-6a4d-4dfe-95ec-4e7385f155a4",
                    "name": "畢尤卡片",
                    "star": 4,
                    "comments": [
                        "MATK+10% 及抗冰凍效果，不差，但是也沒有一定要用，畢竟現在有變異卡利斯格卡了，現在主要看他的是抗冰效果。"
                    ]
                },
                {
                    "id": "7a6c64a0-91fa-4203-8cab-7acc32e44330",
                    "name": "愛麗絲女僕卡片",
                    "star": 3,
                    "comments": [
                        "優秀的BOSS減傷卡，但被小怪打會變痛，要自己取捨。我自己是沒有單刷的需求，不會刻意去稱防禦，因為攻擊就是最好的防禦，坦就交給專業的坦。"
                    ]
                }
            ]
        },
        {
            "categoryCode": "robe",
            "items": [
                {
                    "id": "b5e6dcc4-d27e-4b4d-84e2-8a504f79bda1",
                    "name": "時光超越者斗篷",
                    "star": 5,
                    "comments": [
                        "台服特別裝，原本跟智斗互有輸贏，但自從超越斗也開放附魔後就幾乎是全面超越智斗，畢竟+12情況下單件裝備延遲就能達到24%，算是非常好用，如果不缺延遲也能附MATK%。"
                    ]
                },
                {
                    "id": "f45cd689-cca2-46f7-8bbe-0c5e4ec2a50f",
                    "name": "時光智慧斗篷",
                    "star": 4.5,
                    "comments": [
                        "加蠻多傷害的斗篷，還能附魔15%減延遲，非常強力，雖然超越斗開放附魔後變得沒這麼香，但其實本身效果還是很好。"
                    ]
                },
                {
                    "id": "303af360-e7f4-4d2a-94ba-56ad0aabaf76",
                    "name": "戰死者斗篷",
                    "star": 2,
                    "comments": [
                        "可以搭配EDDA研究所的邪惡氣息頭下，可是對火咒幫助有限，有高精練的可以拿來插滅絕狂暴木乃伊增加火傷。"
                    ]
                },
                {
                    "id": "6ff97def-8545-4ee4-a876-c664cd2007fa",
                    "name": "糖果袋背包(魔法)",
                    "star": 3,
                    "comments": [
                        "過氣裝，主要看附魔。"
                    ]
                },
                {
                    "id": "31f7cda7-81a1-4a0e-ae07-d61fdf649f07",
                    "name": "生存斗篷",
                    "star": 0.5,
                    "comments": [
                        "主要是搭配奉承，但現在奉承也過氣了。"
                    ]
                },
                {
                    "id": "2bc71969-fa48-405f-9868-9333654a79ce",
                    "name": "幻影生存斗篷",
                    "star": 1,
                    "comments": [
                        "我覺得平民也可以考慮這個幻影生存斗篷+生存杖+修行者魔球，三件裝都可以靠自己做，材料我覺得還不算太難。"
                    ]
                },
                {
                    "id": "afa01e74-b63f-4fef-acbf-01943a90c922",
                    "name": "2018-RTC紀念斗篷",
                    "star": 2,
                    "comments": [
                        "可以有三條附魔，有用的就延遲、攻速、BOSS傷害和BOSS無視魔防，主要是破BOSS魔防，不想用風暴套的選擇。"
                    ]
                },
                {
                    "id": "0238f086-d217-4e0d-87c3-2068b4f1ee0b",
                    "name": "巨神蟒蛇皮",
                    "star": 2,
                    "comments": [
                        "副本掉落的超平民裝備，掉落時就已經有精煉和附魔，提供大量的素質讓你輕鬆無詠，搭配時光靴還能+血，如果是缺素質的人就選擇這個吧，而且特I/特D在+12時也有+1攻速，但已經蠻過氣了，有高精煉的可以拿來插滅絕狂暴木乃伊增加火傷。"
                    ]
                },
                {
                    "id": "98a77616-fc0e-4a91-9d6a-b195b7ec6acb",
                    "name": "爭戰披肩",
                    "star": 2,
                    "comments": [
                        "2019新年活動開放打洞和附魔，大大強化了這件裝的實用性，基本上能附的就跟RTC差不多，對咒術來說主要是可以搭配爭戰一套來減地牛的CD，我把他歸類為練功裝，吃王由於秒2的限制不好發揮。"
                    ]
                },
                {
                    "id": "142be9bf-bf4a-4252-9145-9a685cb22877",
                    "name": "思念者斗篷",
                    "star": 1,
                    "comments": [
                        "搭配戰死頭效果還是很爛，不建議用。"
                    ]
                },
                {
                    "id": "ffb48d65-ec41-4776-90fa-f2a07087a97a",
                    "name": "幻象推進翼B型",
                    "star": 3,
                    "comments": [
                        "17.1後平民的新選擇B甲B批B靴整套穿了後能夠很輕鬆的撐裝備無詠和固詠，平民火咒可以考慮。"
                    ]
                },
                {
                    "id": "b608947b-69fd-4aa7-8814-c518e8ac6aa2",
                    "name": "施密特國王斗篷",
                    "star": 3,
                    "comments": [
                        "我覺得看點就是附魔三個魔5吧，有點像以前墮天使，但會選這個得我想應該都是為了搭配其他裝備的套裝效果吧。"
                    ]
                },
                {
                    "id": "155a89bf-2f56-44b4-9025-c853c68e3aeb",
                    "name": "主教斗篷",
                    "star": 3,
                    "comments": [
                        "雖然有加對惡魔傷害，但也不多，主要是要跟主教長靴一起穿，搭配智慧長袍的三件套效果，但我個人不建議去湊套裝，因為斗篷跟鞋子本身的效果實在不怎麼樣。"
                    ]
                },
                {
                    "id": "84459654-6565-494a-94e9-0656941e232e",
                    "name": "天龍披風",
                    "star": 0.5,
                    "comments": [
                        "搭配藍龍鎧甲的披風，但我個人認為就算要用也不會去湊套裝，本身效果太差了。"
                    ]
                },
                {
                    "id": "da4824ba-46aa-4410-8993-387aea7ae3d0",
                    "name": "世界之光●阿斯富力咖",
                    "star": 5,
                    "comments": [
                        "SE城戰的新神器，恐怖的全屬體型增傷30%傲視所有披肩，又有全屬性抗性30%可以抵銷100%屬性增傷這類卡片的副作用，還有延遲10%和20%血量，非常破格的裝備，但現在應該是非常稀有，價格應該是很恐怖，想給6星評價，但因為價錢扣1顆星。"
                    ]
                },
                {
                    "id": "1079c679-9711-461f-9ebd-c26512cbd8c6",
                    "name": "永恆之翼",
                    "star": 3,
                    "comments": [
                        "本來是超級過氣裝，但後來出了一個永恆波利氣球補強，也算是目前能用的平民裝了，如果能附到魔力1或2再搭配碧血玫瑰杖的第四洞附魔魔力1或2，就能直接觸發大神官手套，不用浪費一格飾品去裝RWC墜子。"
                    ]
                },
                {
                    "id": "7041b18f-dcab-4fe3-b3fe-66b99309c226",
                    "name": "全自動推進翼B型",
                    "star": 3.5,
                    "comments": [
                        "主要是跟自動甲做搭配，平民可以用，17.2的自動版本比起上一代幻象，本身能力有比較好，附魔也選擇變多變好，而且如果附兩個Cast就很容易撐裝備無詠。"
                    ]
                }
            ],
            "cards": [
                {
                    "id": "b9d59d7e-f2a1-4f9f-97cd-5b55e9e4fc6b",
                    "name": "深海魔女卡片",
                    "star": 5,
                    "comments": [
                        "火暗屬性魔法傷害+100%，火咒的夢幻逸品。"
                    ]
                },
                {
                    "id": "10c3965b-8c1f-457c-b4cb-b2c7da6420eb",
                    "name": "闇●咒術士 凱特莉娜卡片",
                    "star": 3,
                    "comments": [
                        "我覺得這系列卡片設計者沒有想過法系披肩卡的重要性，要做一張最強神卡除非是全屬性+100%傷害，不然這種卡片只適合物理系。搭配的真咒卡是碧血隕石，連發能力很低，觸發後也沒辦法打多少發，而且由於本身連發能力就不強，能不能順利觸發也是個問題，這張卡還是玩具性質居多。"
                    ]
                },
                {
                    "id": "b640a165-77a2-4937-87eb-df12116e016f",
                    "name": "沼澤捲甲蟲卡片",
                    "star": 1,
                    "comments": [
                        "平民泛用卡片，但火咒不缺攻速，而且有更好的滅絕狂暴木乃伊可以用。"
                    ]
                },
                {
                    "id": "525c2498-e367-4e05-8a82-679ededcf965",
                    "name": "惡魔波利卡片",
                    "star": 1.5,
                    "comments": [
                        "練功蠻好用的卡片，被怪打會變不痛，可以比較放鬆的不怕掉呆，前提是你少了披肩卡還是打得很順拉。"
                    ]
                },
                {
                    "id": "6d72addf-f1a0-4e7f-afeb-5c1d11de0e9b",
                    "name": "滅絕狂暴木乃伊卡片",
                    "star": 4.5,
                    "comments": [
                        "一般人的首選，增加火傷!"
                    ]
                }
            ]
        },
        {
            "categoryCode": "shoes",
            "items": [
                {
                    "id": "956b8fb6-5cc0-4ce9-ad7c-a649233a3b56",
                    "name": "時光超越者之靴",
                    "star": 3.5,
                    "comments": [
                        "雖然是適合咒術的鞋子，因為有固詠又有MATK、攻速，而且可以很方便得跟其他職業包含擴充職業共用，不過滅世靴出來後，大概只有打人形怪時，才會有大神官超越靴出場的機會。"
                    ]
                },
                {
                    "id": "19f7da04-de80-4ca4-b94d-9992a983fe3b",
                    "name": "幻象戰靴B型",
                    "star": 3,
                    "comments": [
                        "平民可以選擇這雙鞋子，固詠-0.7秒非常好撐1秒，而且又非常好取得。魔力風暴算是沒有副作用的魔暴，雖然加得比較少，但不會扣SP我覺得不錯。"
                    ]
                },
                {
                    "id": "ddcb15d5-160b-4e18-b719-beee6eeb8fb4",
                    "name": "時光靈巧戰靴",
                    "star": 2.5,
                    "comments": [
                        "D靴好處是很方便撐素質無詠，+12就+12DEX，對配點非常友善，和有減固詠，不過火咒剛好都不缺。"
                    ]
                },
                {
                    "id": "8e6b622d-fa08-445a-91cd-296f972d1432",
                    "name": "時光智慧戰靴",
                    "star": 3,
                    "comments": [
                        "用戰死頭的火咒剛好可以用這雙搭配智斗，不過我覺得現在是滅世靴的天下。"
                    ]
                },
                {
                    "id": "ad3da4a9-0d73-4efc-93fa-cee0d2df89b9",
                    "name": "阿斯特莉亞戰靴",
                    "star": 0.5,
                    "comments": [
                        "這雙鞋子主要就是固詠-0.5秒和延遲-5%和攻速+8%，缺延遲的可以用，搭配阿斯特莉亞指環可以再多5%延遲，可是火咒剛好都不缺。"
                    ]
                },
                {
                    "id": "1efd77d7-f1a3-4639-b1dc-a62d2452185f",
                    "name": "火雷大神靴",
                    "star": 2.5,
                    "comments": [
                        "這雙鞋子+很多MATK和MDEF，本來致命缺點是沒有減固詠，但用戰死頭剛好不缺固詠，不過台服版本被閹割砍了一大刀。可以等等看未來有沒有覺醒版的，雖然來台灣應該是大改造，但還是能稍微看看。"
                    ]
                },
                {
                    "id": "837e046d-270c-4619-8d2a-7f5f4abe33e2",
                    "name": "大法師爭戰戰靴",
                    "star": 0.5,
                    "comments": [
                        "搭配爭戰衣和爭戰披來扣地牛CD的鞋子，只有玩地牛型的咒術才會考慮。"
                    ]
                },
                {
                    "id": "7b38a963-b377-449a-9079-4ff6f0a8c73e",
                    "name": "守護精靈祈禱之鞋",
                    "star": 3,
                    "comments": [
                        "主要是看上搭配尼德霍格幻影卡片的BOSS增傷效果，不過還是沒有滅世靴好用。"
                    ]
                },
                {
                    "id": "4732ea2d-def3-4e3e-ad12-755ec8df8c33",
                    "name": "主教長靴",
                    "star": 0.5,
                    "comments": [
                        "主要是搭配智慧長袍、主教斗篷一起穿的三件套裝效果，但本身效果太爛而且還是加物理系傷害，不建議湊套裝。"
                    ]
                },
                {
                    "id": "564f2045-a384-4043-9de6-876dac33c3f7",
                    "name": "天龍戰靴",
                    "star": 0.5,
                    "comments": [
                        "搭配藍龍鎧甲的鞋子，但我個人認為就算要用也不會去湊套裝，本身效果太差了。"
                    ]
                },
                {
                    "id": "ac1e760d-aa50-4739-88c4-265baafb53b8",
                    "name": "滅世魔靴",
                    "star": 5,
                    "comments": [
                        "新出的超強神靴，加一大堆傷害還有減少碧血隕石的CD，幾乎是所有法系的首選鞋。而且練功的時候那個被打觸發毀滅彗星的機率非常高，高到被G社砍了一刀機率後還是很高，練迷藏這種怪一堆的圖真的是掛著不動就能清怪了，不過前提是你要夠硬撐得住就是了拉。"
                    ]
                },
                {
                    "id": "28a304b9-c846-4b82-8eb8-dfb1f3cea2cc",
                    "name": "全自動戰靴B型",
                    "star": 3.5,
                    "comments": [
                        "升級版的幻象戰靴，平民好用。"
                    ]
                }
            ],
            "cards": [
                {
                    "id": "0f45041a-e1df-4c7e-aa50-c7be8602081c",
                    "name": "墮落大神官卡片",
                    "star": 4,
                    "comments": [
                        "對人型、天使型魔法傷害+50%，稀有的鞋子增傷卡片，而且還加蠻多的，不過滅世靴出來後，這張卡片只剩下打人型的作用。"
                    ]
                },
                {
                    "id": "f0db0c11-cf7c-48d5-8ec0-308a3d2914df",
                    "name": "封印墮落大神官 悉潘卡片",
                    "star": 3,
                    "comments": [
                        "正卡效果一半，副作用沒變多，不過滅世靴出來後連正卡都已經下神壇，封印的就算打人型王搞不好還會輸滅世靴。"
                    ]
                },
                {
                    "id": "67d95536-bdbe-4bee-ae9d-322eedc680bc",
                    "name": "滅絕木乃伊犬卡片",
                    "star": 3.5,
                    "comments": [
                        "平民好物，純粹加MATK10%的卡，沒有副作用。"
                    ]
                },
                {
                    "id": "5d062a96-cfd2-4cc4-bb9c-e1e1033c2762",
                    "name": "月夜貓卡片",
                    "star": 2,
                    "comments": [
                        "搭配火雷大神靴使用，其他都不需要這張卡。"
                    ]
                },
                {
                    "id": "ceb249eb-4d48-4edb-8b43-0d6af37d90d6",
                    "name": "暴虐甜餅人卡片",
                    "star": 0.5,
                    "comments": [
                        "超沒用的卡片，滅絕木乃伊犬卡片還加比較多又沒副作用，不知道這張卡存在的意義是?"
                    ]
                },
                {
                    "id": "62695ef9-9e31-4fee-8317-c051c8bbb640",
                    "name": "吉芬小偷卡片",
                    "star": 1,
                    "comments": [
                        "加太少，不夠看。"
                    ]
                },
                {
                    "id": "a2e462ec-a215-4447-86cb-0e0e65b96de4",
                    "name": "大賽吉芬小偷卡片",
                    "star": 1.5,
                    "comments": [
                        "加太少，不夠看。"
                    ]
                },
                {
                    "id": "18c4b573-2836-4997-8dcf-1a5cf328950c",
                    "name": "黑暗之王卡片",
                    "star": 5,
                    "comments": [
                        "搭配滅世靴的唯一卡片，因為滅世靴的強大導致這張變成首選，這張卡本身效果完全沒有用。"
                    ]
                },
                {
                    "id": "6312d4d6-8e96-4e30-ba34-6513b79c3238",
                    "name": "研究助理機器人卡片",
                    "star": 1,
                    "comments": [
                        "主要是為了使用流浪魔法書套卡才會插的卡，不過這套卡卡到太多增傷卡，我不推薦。"
                    ]
                }
            ]
        },
        {
            "categoryCode": "acc",
            "items": [
                {
                    "id": "2af83e55-cb81-4a7b-8a2a-a5efb3b05af4",
                    "name": "席琳的胸針",
                    "star": 5,
                    "comments": [
                        "搭配席琳的蝴蝶結有巨量的BOSS增傷，不過因為我打王不會用火咒所以我就沒有用這個。"
                    ]
                },
                {
                    "id": "6a3b55cd-25a8-4d3e-aeb3-6e8380fd7861",
                    "name": "基米的胸針",
                    "star": 5,
                    "comments": [
                        "一樣是搭配席琳的蝴蝶結可以有巨量的MATK和各種法傷加成，可以跟席琳胸針疊加，形成席琳三件套裝，有席琳+基米胸針就像有雙雷腰一樣強大。席琳胸針當初是引進日版的席琳胸針，後來引進了韓版席琳胸針，因為同名的關係就改成基米的胸針。"
                    ]
                },
                {
                    "id": "1a10c5c9-1e9f-4c20-abc6-553dae72ae83",
                    "name": "狄克推多項鍊",
                    "star": 3,
                    "comments": [
                        "搭配朱比特輕甲等凱薩裝備的飾品，套裝有體型法傷，如果有用朱比特可以考慮。"
                    ]
                },
                {
                    "id": "06935e6e-26f6-4f97-ad94-e8aa6f74f16a",
                    "name": "阿斯特莉亞指環",
                    "star": 3,
                    "comments": [
                        "這個裝備是搭配神官王卡片可以有不俗的BOSS增傷，搭配阿斯靴還能多減延遲，但由於綁定神官王卡所以比較綁裝一點。"
                    ]
                },
                {
                    "id": "2402d49d-3f79-4895-a05d-ec5950a5dfed",
                    "name": "專家戒指",
                    "star": 0.5,
                    "comments": [
                        "延遲用不到。"
                    ]
                },
                {
                    "id": "e64298b2-e5fb-4219-a1db-6fec667d2f4c",
                    "name": "大神官手套",
                    "star": 3.5,
                    "comments": [
                        "火咒有機會可以用碧血玫瑰杖和永恆之翼的附麼直接搞定魔力1和2附魔。"
                    ]
                },
                {
                    "id": "8ed92942-d345-4958-be92-0da6612fc158",
                    "name": "RWC紀念墜子",
                    "star": 3,
                    "comments": [
                        "主要是要他的魔12附魔，方便搭配大神官手套用的。"
                    ]
                },
                {
                    "id": "0fc110ff-c400-4c15-abd5-57904414cdeb",
                    "name": "施密特國王徽章(INT)",
                    "star": 3,
                    "comments": [
                        "平民好物，搭配時光靴的暴走魔法附魔有額外增傷，還能附魔魔力減變詠，對於平民小資撐裝備無詠也非常有幫助，可是會卡到滅世靴。"
                    ]
                },
                {
                    "id": "ee0d3ea7-0c3b-401d-b745-5dfc696a2e94",
                    "name": "幻象戰戒",
                    "star": 3.5,
                    "comments": [
                        "搭配不同幻象飾品可以有不同效果，看是要boss傷害還是減固詠，減固詠的話如果搭配幻象戰靴就能直接達到減1秒的門檻，平民不錯用。"
                    ]
                },
                {
                    "id": "28d67eaa-e287-412f-9fb3-5278d0a59109",
                    "name": "幻象戰鬥晶片R",
                    "star": 3,
                    "comments": [
                        "EP17.1後，解任務就能獲得的高CP飾品，平民福音，可以搭配幻象戰戒來增加傷害。"
                    ]
                },
                {
                    "id": "b67f7518-ba0d-4581-9eb2-12714ad2720c",
                    "name": "幻象戰鬥晶片L",
                    "star": 3,
                    "comments": [
                        "EP17.1後，解任務就能獲得的高CP飾品，平民福音，可以搭配幻象戰戒來減固詠。"
                    ]
                },
                {
                    "id": "3bc77d3e-1ffa-4f24-b371-0b379631a767",
                    "name": "時光超越者手鐲",
                    "star": 2,
                    "comments": [
                        "這個裝備對法系來說加的東西沒有到非常多，我個人覺得這東西得看點是搭配超越斗的時候有15%全種族破防，搭配+20職業2.0手盾套的60%全種族破防，以及主教的贖罪25%全種族，就可以達到100%全種族破防。但超越靴的部分就卡到滅世靴了，所以我不推薦這個。"
                    ]
                },
                {
                    "id": "e1f44aef-ff39-4bb3-985c-9612bb080852",
                    "name": "時光超越者之戒",
                    "star": 0.5,
                    "comments": [
                        "這東西很莫名其妙，掛著超越的名子，主要卻是搭配一般的時光靴?而且只能觸發一個不怎麼樣的效果真的蠻爛的，同樣類型的國王徽章都屌打這個。"
                    ]
                },
                {
                    "id": "47170d88-691e-49c0-a6d0-fd9afd044206",
                    "name": "思念體破壞因子研究錄(法師篇)",
                    "star": 0.5,
                    "comments": [
                        "主要是毀滅彗星和減固詠用的，我覺得火咒不適合。"
                    ]
                },
                {
                    "id": "caad13bc-a1e1-49a8-9ada-d448d7088603",
                    "name": "思念之戒",
                    "star": 0.5,
                    "comments": [
                        "需要搭配王卡但卻給很爛的效果，感覺主要用處應該是搭配思念體破壞因子研究錄去戰死印卡用的吧。可是我覺得能去印卡的應該也不缺這20%傷害，而且戰死裡面都是boss級怪物，魔導王卡也沒用。"
                    ]
                },
                {
                    "id": "8d8d789b-7379-4d47-a861-fd5469ad7a48",
                    "name": "全自動戰鬥晶片R",
                    "star": 3.5,
                    "comments": [
                        "升級版的幻象晶片，本身有多加HP，附魔有多一個[全部力量]，解決了以前第三個附魔沒有有用的選擇的問題。"
                    ]
                },
                {
                    "id": "21ca1c9c-59ca-4985-9c62-00edf32ac252",
                    "name": "全自動戰鬥晶片L",
                    "star": 3.5,
                    "comments": [
                        "升級版的幻象晶片，本身有多加HP，附魔有多一個[全部力量]，解決了以前第三個附魔沒有有用的選擇的問題。"
                    ]
                },
                {
                    "id": "7754deab-917c-4710-97a4-7f7825a238ea",
                    "name": "聖光藍寶石項鍊",
                    "star": 4.5,
                    "comments": [
                        "天使惡魔特化裝備，打挑戰好用，好處是不綁頭上，附魔很好的在指定的種族上傷害甚至可以超越席琳套。"
                    ]
                },
                {
                    "id": "f7f8eea9-2e6a-4994-ab79-d8fde2883428",
                    "name": "聖光藍寶石戒指",
                    "star": 4.5,
                    "comments": [
                        "天使惡魔特化裝備，打挑戰好用，好處是不綁頭上，附魔很好的在指定的種族上傷害甚至可以超越席琳套，套裝效果主要是搭配項鍊，而本身搭配古代澳丁系列的裝備的效果則是因為斗篷和鞋子幾乎沒有用，所以不推薦觸發。"
                    ]
                },
                {
                    "id": "1eea82b2-b01f-4724-ad6a-c0bfe9f9153d",
                    "name": "撒旦藍寶石項鍊",
                    "star": 4.5,
                    "comments": [
                        "天使龍族特化裝備，除了對應種族不同以外，其他都同聖光系列，現階段較冷門，但未來星座塔開放後，對應龍族的裝備可能就會熱門起來。"
                    ]
                },
                {
                    "id": "e99834bf-7446-4fe1-9d46-827f877c2464",
                    "name": "撒旦藍寶石戒指",
                    "star": 4.5,
                    "comments": [
                        "天使龍族特化裝備，除了對應種族不同以外，其他都同聖光系列，現階段較冷門，但未來星座塔開放後，對應龍族的裝備可能就會熱門起來。"
                    ]
                }
            ],
            "cards": [
                {
                    "id": "f8fde2fa-1ba1-4c9c-94a9-3f56828ab8b9",
                    "name": "森林妖精卡片",
                    "star": 5,
                    "comments": [
                        "首選卡，火地+20%傷害絕對是沒有其他能替代的。"
                    ]
                },
                {
                    "id": "a164563f-2434-4bd2-ab7d-ac5a149ea856",
                    "name": "甲蟲卡片",
                    "star": 0.5,
                    "comments": [
                        "完全不建議使用，埃維亞已經很便宜了。"
                    ]
                },
                {
                    "id": "6ccba962-f20e-4e1f-9aa0-c88f5dff8090",
                    "name": "貝雷傑卡片",
                    "star": 1,
                    "comments": [
                        "想撐裝備無詠的人用，但我覺得最好還是不要用貝雷傑，可以靠其他裝備撐，飾品還是插增傷好。"
                    ]
                },
                {
                    "id": "42114588-7638-437f-b318-632cdb698890",
                    "name": "封印貝雷傑卡片",
                    "star": 1,
                    "comments": [
                        "同正卡。"
                    ]
                },
                {
                    "id": "dfe94d2b-54f2-43e5-9ab8-d3b8be185f5d",
                    "name": "流浪魔法書卡片",
                    "star": 1,
                    "comments": [
                        "主要功能是套卡效果，但我覺得犧牲太多增傷卡部位，導致有點繞遠路的感覺。"
                    ]
                }
            ]
        },
        {
            "categoryCode": "shadow",
            "items": [
                {
                    "id": "b3070548-1831-4e13-98f6-064ee6742493",
                    "name": "影子碧血隕石套裝(盾/鎧/靴)",
                    "star": 5,
                    "comments": [
                        "加蠻多碧血隕石傷害，不過其實沒有非常必要，因為真咒兩張就加很多了，這套算錦上添花。"
                    ]
                },
                {
                    "id": "0765705c-359e-49e6-8b3e-fdd862aa152f",
                    "name": "影子風暴套裝(鎧/盾/靴)",
                    "star": 1,
                    "comments": [
                        "卡到碧血隕石套。"
                    ]
                },
                {
                    "id": "eea01e11-64d0-4221-b208-8bcd5d194fe7",
                    "name": "影子風暴套裝(手/耳/墜)",
                    "star": 4.5,
                    "comments": [
                        "可以考慮要用這套還是要用職業2.0來破防，打小怪的話我覺得2.0配贖罪就夠了。"
                    ]
                },
                {
                    "id": "cb51cd34-dc35-489f-a796-b649e7f39d13",
                    "name": "影子咒術士套(手/耳/墜/鎧/盾/靴)",
                    "star": 4,
                    "comments": [
                        "可以用碧血隕石套搭配咒術手套使用，最高有60%全種族破防，搭配贖罪就有85%，打小怪綽綽有餘了。"
                    ]
                },
                {
                    "id": "d7db7d72-4fcb-453a-aae4-770a2eba2dc9",
                    "name": "影子全能套裝(耳/墜)",
                    "star": 3,
                    "comments": [
                        "錦上添花的東西，如果有閒置的可以拿來用。"
                    ]
                },
                {
                    "id": "26a0403f-2f4b-4561-91d8-ca5031b22f29",
                    "name": "影子天衣無縫風暴套裝(鎧/靴)",
                    "star": 1,
                    "comments": [
                        "兩件就無視全種族，卡到碧血套，建議用耳墜。"
                    ]
                },
                {
                    "id": "faabf757-a9f4-4a86-9633-db742f117016",
                    "name": "影子天衣無縫風暴套裝(耳/墜)",
                    "star": 5,
                    "comments": [
                        "兩件就無視全種族，非常強力，省去了切裝的困擾。"
                    ]
                }
            ],
            "cards": []
        },
        {
            "categoryCode": "costume",
            "items": [
                {
                    "id": "12aa0b2d-528b-4030-b6ae-5e21a7624033",
                    "name": "咒術士石套(披肩/頭上/頭中/頭下)",
                    "star": 5,
                    "comments": [
                        "火咒唯一選擇，其他都是捨近求遠。"
                    ]
                }
            ],
            "cards": []
        },
        {
            "categoryCode": "pet",
            "items": [
                {
                    "id": "31ae7ab2-b6cc-4077-a51c-efbd4fc10969",
                    "name": "幽暗夢魘",
                    "star": 5,
                    "comments": [
                        "非常親密時有7%加火屬性傷害和40MATK，不無小補，不過MVP寵價錢很高，CP值蠻低的。"
                    ]
                },
                {
                    "id": "4acb1c9f-692d-445b-8e75-15587d2d61c0",
                    "name": "異型",
                    "star": 3.5,
                    "comments": [
                        "有時候可能就差2點DEX就能無詠，我覺得有機會派上用場。"
                    ]
                },
                {
                    "id": "2c3165a3-0c3d-4e63-acd1-18beb9f813ea",
                    "name": "狂暴小土人",
                    "star": 2,
                    "comments": [
                        "老實說4%MATK基本上是沒啥感覺，比魔攻石套還少，就是養好看的。"
                    ]
                },
                {
                    "id": "776adf40-75e7-4f08-a415-85e1c3afca8c",
                    "name": "赤焰小惡魔",
                    "star": 1,
                    "comments": [
                        "2%MATK，其實沒啥用，主要就是可愛。"
                    ]
                },
                {
                    "id": "31e94ab9-c64c-410f-8c45-8d047669a8f1",
                    "name": "堅硬七彩夢魘",
                    "star": 4,
                    "comments": [
                        "台服還沒出，非常親密有4點INT，跟異型一樣，有時候可能就差這一點就無詠了，我覺得未來很有機會派上用場。"
                    ]
                }
            ],
            "cards": []
        }
    ]
}